query_counter/__init__.py
tests/__init__.py
tests/conftest.py
tests/models.py
tests/test_query_counter.py
query_counter-0.3.1.dist-info/LICENSE
query_counter-0.3.1.dist-info/METADATA
query_counter-0.3.1.dist-info/WHEEL
query_counter-0.3.1.dist-info/top_level.txt
query_counter-0.3.1.dist-info/RECORD
