Metadata-Version: 2.1
Name: query-counter
Version: 0.3.1
Summary: SQLAlchemy model N+1 debugger
Home-page: https://github.com/tatari-tv/query-counter
Author: brian-tatari
Author-email: brian.olecki@tatari.tv
License: MIT
Keywords: query counter debugger n+1 sqlalchemy
Platform: UNKNOWN
Classifier: Development Status :: 4 - Beta
Classifier: Intended Audience :: Developers
Classifier: License :: OSI Approved :: MIT License
Classifier: Programming Language :: Python :: 3.8
Classifier: Programming Language :: Python :: 3.9
Classifier: Programming Language :: Python :: 3.10
License-File: LICENSE
Requires-Dist: SQLAlchemy (>=1.4.0)
